Metadata-Version: 2.1
Name: shell2trickle
Version: 1.0.4
Summary: use shell2trickle to post your new trickle!
Home-page: UNKNOWN
Author: Lania Kea
Author-email: lania.dang@visionwx.com
License: MIT
Keywords: shell trickle
Platform: UNKNOWN
Classifier: Programming Language :: Python :: 3
Classifier: License :: OSI Approved :: MIT License
Classifier: Operating System :: OS Independent
